Workbook
Name aporte: Planilha1!$D$15
Name patrimonio: Planilha1!$D$18
Name qtd_anos: Planilha1!$D$16
Name rendimento_carteira: Planilha1!$D$11
Name salario: Planilha1!$D$10
Name susgetao_investimento: Planilha1!$D$12
Name taxa_mensal: Planilha1!$D$17

Sheet Planilha1
B9: CONFIGURAÇÕES
B10: Salário | D10: 5000
B11: Rendimento Carteira | D11: 0.006
B12: Sugestão de Investimento | D12: =D10*30% -> 1500
B14: INVESTIMENTO MENSAL
B15: Quanto investir por mês? | D15: 500
B16: Por quantos anos? | D16: 5
B17: Taxa de rendimento mensal? | D17: 0.0108
B18: Patrimônio acumulado? | D18: =FV(taxa_mensal,qtd_anos*12,aporte*-1) -> 41902.01
B19: Dividendos mensais? | D19: =patrimonio*rendimento_carteira -> 251.41206
B21: CENÁRIOS | D21: DIVIDENDO
A22: 2 | B22: Quanto em 2 anos? | C22: =FV($D$17,$A22*12,$D$15*-1) -> 13615.432 | D22: =C22*rendimento_carteira -> 81.692591
A23: 5 | B23: Quanto em 5 anos? | C23: =FV($D$17,$A23*12,$D$15*-1) -> 41902.01 | D23: =C23*rendimento_carteira -> 251.41206
A24: 10 | B24: Quanto em 10 anos? | C24: =FV($D$17,$A24*12,$D$15*-1) -> 121728.83 | D24: =C24*rendimento_carteira -> 730.373
A25: 20 | B25: Quanto em 20 anos? | C25: =FV($D$17,$A25*12,$D$15*-1) -> 563524.5 | D25: =C25*rendimento_carteira -> 3381.147
A26: 30 | B26: Quanto em 30 anos? | C26: =FV($D$17,$A26*12,$D$15*-1) -> 2166952.4 | D26: =C26*rendimento_carteira -> 13001.714
B28: PERFIL | C28: AGRESSIVO
B29: VALOR A SER INVESTIDO POR MÊS | C29: =aporte -> 500
B31: TIPO DE FII | C31: PERCENTUAL SUGERIDO | D31: VALORES
B32: PAPEL | C32: =VLOOKUP($C$28&"-"&B32,Planilha2!$A$1:$D$22,4,FALSE) -> 0.5 | D32: =C32*aporte -> 250
B33: TIJOLO | C33: =VLOOKUP($C$28&"-"&B33,Planilha2!$A$1:$D$22,4,FALSE) -> 0.1 | D33: =C33*aporte -> 50
B34: HÍBRIDOS | C34: =VLOOKUP($C$28&"-"&B34,Planilha2!$A$1:$D$22,4,FALSE) -> 0.05 | D34: =C34*aporte -> 25
B35: FOFs | C35: =VLOOKUP($C$28&"-"&B35,Planilha2!$A$1:$D$22,4,FALSE) -> 0.05 | D35: =C35*aporte -> 25
B36: DESENVOLVIMENTO | C36: =VLOOKUP($C$28&"-"&B36,Planilha2!$A$1:$D$22,4,FALSE) -> 0.2 | D36: =C36*aporte -> 100
B37: HOTELARIA | C37: =VLOOKUP($C$28&"-"&B37,Planilha2!$A$1:$D$22,4,FALSE) -> 0.1 | D37: =C37*aporte -> 50
D38: =SUM(D32:D37) -> 500

Sheet Planilha2
A2: CHAVE | B2: PERFIL | C2: TIPO DE FII | D2: %
A3: =B3&"-"&C3 -> CONSERVADOR-PAPEL | B3: CONSERVADOR | C3: PAPEL | D3: 0.3
A4: =B4&"-"&C4 -> CONSERVADOR-TIJOLO | B4: CONSERVADOR | C4: TIJOLO | D4: 0.5
A5: =B5&"-"&C5 -> CONSERVADOR-HÍBRIDOS | B5: CONSERVADOR | C5: HÍBRIDOS | D5: 0.1 | G5: %
A6: =B6&"-"&C6 -> CONSERVADOR-FOFs | B6: CONSERVADOR | C6: FOFs | D6: 0.1 | F6: MODERADO-TIJOLO | G6: =VLOOKUP(F6,$A:$D,4,FALSE) -> 0.35
A7: =B7&"-"&C7 -> CONSERVADOR-DESENVOLVIMENTO | B7: CONSERVADOR | C7: DESENVOLVIMENTO | D7: 0
A8: =B8&"-"&C8 -> CONSERVADOR-HOTELARIA | B8: CONSERVADOR | C8: HOTELARIA | D8: 0
A9: =B9&"-"&C9 -> MODERADO-PAPEL | B9: MODERADO | C9: PAPEL | D9: 0.32
A10: =B10&"-"&C10 -> MODERADO-TIJOLO | B10: MODERADO | C10: TIJOLO | D10: 0.35
A11: =B11&"-"&C11 -> MODERADO-HÍBRIDOS | B11: MODERADO | C11: HÍBRIDOS | D11: 0.08
A12: =B12&"-"&C12 -> MODERADO-FOFs | B12: MODERADO | C12: FOFs | D12: 0.05
A13: =B13&"-"&C13 -> MODERADO-DESENVOLVIMENTO | B13: MODERADO | C13: DESENVOLVIMENTO | D13: 0.1
A14: =B14&"-"&C14 -> MODERADO-HOTELARIA | B14: MODERADO | C14: HOTELARIA | D14: 0.1
A15: =B15&"-"&C15 -> AGRESSIVO-PAPEL | B15: AGRESSIVO | C15: PAPEL | D15: 0.5
A16: =B16&"-"&C16 -> AGRESSIVO-TIJOLO | B16: AGRESSIVO | C16: TIJOLO | D16: 0.1
A17: =B17&"-"&C17 -> AGRESSIVO-HÍBRIDOS | B17: AGRESSIVO | C17: HÍBRIDOS | D17: 0.05
A18: =B18&"-"&C18 -> AGRESSIVO-FOFs | B18: AGRESSIVO | C18: FOFs | D18: 0.05
... A20: =B20&"-"&C20 -> AGRESSIVO-HOTELARIA | B20: AGRESSIVO | C20: HOTELARIA | D20: 0.1
